Benchmark/__init__.py
Benchmark/aws/Amazon EC2 Instance Comparison.csv
Benchmark/bfunctions.py
Benchmark/byteformat.py
Benchmark/classes.py
Benchmark/run.py
benchmark_4dn-0.5.28.dist-info/LICENSE.txt
benchmark_4dn-0.5.28.dist-info/METADATA
benchmark_4dn-0.5.28.dist-info/WHEEL
benchmark_4dn-0.5.28.dist-info/RECORD
