Metadata-Version: 2.1
Name: benchmark-4dn
Version: 0.5.28
Summary: Benchmark functions that returns total space, mem, cpu given input size and parameters for the CWL workflows
Home-page: https://github.com/4dn-dcic/Benchmark
License: MIT
Keywords: benchmark,cwl,common workflow language,docker,tibanna,bioinformatics,4dn
Author: Alexander Veit
Author-email: alexander_veit@hms.harvard.edu
Requires-Python: >=3.5,<4.0
Classifier: Development Status :: 4 - Beta
Classifier: Intended Audience :: Developers
Classifier: Intended Audience :: Science/Research
Classifier: License :: OSI Approved :: MIT License
Classifier: Operating System :: OS Independent
Classifier: Programming Language :: Python
Classifier: Programming Language :: Python :: 3
Classifier: Programming Language :: Python :: 3.5
Classifier: Programming Language :: Python :: 3.6
Classifier: Programming Language :: Python :: 3.7
Classifier: Programming Language :: Python :: 3.8
Classifier: Programming Language :: Python :: 3.9
Classifier: Programming Language :: Python :: 3.10
Classifier: Programming Language :: Python :: 3.11
Classifier: Programming Language :: Python :: 2.7
Classifier: Programming Language :: Python :: 3
Classifier: Topic :: Scientific/Engineering :: Bio-Informatics
Classifier: Topic :: Software Development :: Libraries :: Python Modules
Project-URL: Repository, https://github.com/4dn-dcic/Benchmark
